odoo/addons/sm_partago_user/__init__.py
odoo/addons/sm_partago_user/__manifest__.py
odoo/addons/sm_partago_user/email_tmpl/cs_complete_data_soci_not_found_email.xml
odoo/addons/sm_partago_user/email_tmpl/cs_missing_data_email.xml
odoo/addons/sm_partago_user/models/__init__.py
odoo/addons/sm_partago_user/models/models_carsharing_update_data.py
odoo/addons/sm_partago_user/models/models_carsharing_user_request.py
odoo/addons/sm_partago_user/models/models_cs_task.py
odoo/addons/sm_partago_user/models/models_sm_company.py
odoo/addons/sm_partago_user/models/models_sm_member.py
odoo/addons/sm_partago_user/models/models_sm_member_csgroup.py
odoo/addons/sm_partago_user/models/models_sm_res_config_settings.py
odoo/addons/sm_partago_user/models/models_smp_carsharing_registration_request.py
odoo/addons/sm_partago_user/models/models_smp_carsharing_registration_wizard.py
odoo/addons/sm_partago_user/models/models_smp_change_email_wizard.py
odoo/addons/sm_partago_user/models/models_smp_user_cron.py
odoo/addons/sm_partago_user/models/models_smp_user_utils.py
odoo/addons/sm_partago_user/security/ir.model.access.csv
odoo/addons/sm_partago_user/views/views.xml
odoo/addons/sm_partago_user/views/views_carsharing_update_data.xml
odoo/addons/sm_partago_user/views/views_carsharing_user_request.xml
odoo/addons/sm_partago_user/views/views_change_email_wizard.xml
odoo/addons/sm_partago_user/views/views_cron.xml
odoo/addons/sm_partago_user/views/views_cs_registration_request.xml
odoo/addons/sm_partago_user/views/views_cs_registration_wizard.xml
odoo/addons/sm_partago_user/views/views_cs_task.xml
odoo/addons/sm_partago_user/views/views_db.xml
odoo/addons/sm_partago_user/views/views_member_cs_groups.xml
odoo/addons/sm_partago_user/views/views_members.xml
odoo/addons/sm_partago_user/views/views_res_config_settings.xml
odoo12_addon_sm_partago_user-12.0.0.1.12.dist-info/METADATA
odoo12_addon_sm_partago_user-12.0.0.1.12.dist-info/WHEEL
odoo12_addon_sm_partago_user-12.0.0.1.12.dist-info/top_level.txt
odoo12_addon_sm_partago_user-12.0.0.1.12.dist-info/RECORD
