Metadata-Version: 2.1
Name: odoo12-addon-sm-partago-user
Version: 12.0.0.1.12
Summary: Handles all carsharing user related data and actions
Home-page: http://www.sommobilitat.coop
Author: Som Mobilitat
License: UNKNOWN
Platform: UNKNOWN
Classifier: Programming Language :: Python
Classifier: Framework :: Odoo
Classifier: Framework :: Odoo :: 12.0
Requires-Python: >=3.5
Requires-Dist: odoo12-addon-sm-partago-db
Requires-Dist: odoo12-addon-vertical-carsharing
Requires-Dist: odoo <12.1dev,>=12.0a
